{
    "project":  {
                    "name":  "Dental-Mina",
                    "signature":  "PYM JBZ"
                },
    "gate":  {
                 "current":  "",
                 "locked_pass":  [

                                 ],
                 "last_pass":  ""
             },
    "last_pass":  "",
    "last_fail":  null,
    "active_issue":  null,
    "next_action_hash":  "d9f06f179be65563f8f106a81ae532b27b8c2442d24b15e72078c2eca42f88ec",
    "updated_utc":  "2026-01-31T02:56:53.4567751Z",
    "locked_pass":  [

                    ]
}